datamason/__init__.py
datamason/analysis/__init__.py
datamason/analysis/analysis.py
datamason/analysis/network_analysis/__init__.py
datamason/analysis/network_analysis/network_analysis.py
datamason/analysis/signal_processing/__init__.py
datamason/analysis/signal_processing/signal_processing.py
datamason/analysis/spatial_analysis/__init__.py
datamason/analysis/spatial_analysis/spatial_analysis.py
datamason/clustering/__init__.py
datamason/clustering/clustering.py
datamason/data_io/__init__.py
datamason/data_io/io.py
datamason/image_processing/__init__.py
datamason/image_processing/image_processing.py
datamason/install_utilities/__init__.py
datamason/install_utilities/install_models.py
datamason/install_utilities/install_polyglot.py
datamason/integrate/__init__.py
datamason/integrate/integrate.py
datamason/interpolate/__init__.py
datamason/interpolate/interpolate.py
datamason/linear_algebra/__init__.py
datamason/linear_algebra/linear_algebra.py
datamason/metrics/__init__.py
datamason/metrics/metrics.py
datamason/modeling/__init__.py
datamason/modeling/modeling.py
datamason/numerics/__init__.py
datamason/numerics/numerical.py
datamason/optimize/__init__.py
datamason/optimize/optimize.py
datamason/preprocessing/__init__.py
datamason/preprocessing/prepare.py
datamason/preprocessing/transform.py
datamason/statistics/__init__.py
datamason/statistics/statistics.py
datamason/test/__init__.py
datamason/test/test.py
datamason/test/test_suite/__init__.py
datamason/test/test_suite/test_analyze.py
datamason/test/test_suite/test_clustering.py
datamason/test/test_suite/test_data_io.py
datamason/test/test_suite/test_image_processing.py
datamason/test/test_suite/test_integrate.py
datamason/test/test_suite/test_interpolate.py
datamason/test/test_suite/test_linear_algebra.py
datamason/test/test_suite/test_machine_learning.py
datamason/test/test_suite/test_network.py
datamason/test/test_suite/test_numerical.py
datamason/test/test_suite/test_numerics.py
DataMason-0.7.1b2.dist-info/LICENSE
DataMason-0.7.1b2.dist-info/METADATA
DataMason-0.7.1b2.dist-info/WHEEL
DataMason-0.7.1b2.dist-info/top_level.txt
DataMason-0.7.1b2.dist-info/RECORD
