Metadata-Version: 2.1
Name: DataMason
Version: 0.7.1b2
Summary: A powerful Python package for data analysis and manipulation.
Home-page: https://github.com/thyripian/datamason
Author: Kevan White (Thyripian)
Author-email: thyripian@gmail.com
License: MIT
Classifier: Development Status :: 4 - Beta
Classifier: Intended Audience :: Developers
Classifier: License :: OSI Approved :: MIT License
Classifier: Programming Language :: Python :: 3
Classifier: Programming Language :: Python :: 3.6
Classifier: Programming Language :: Python :: 3.7
Classifier: Programming Language :: Python :: 3.8
Classifier: Programming Language :: Python :: 3.9
Requires-Python: >=3.6
License-File: LICENSE
Requires-Dist: Flask
Requires-Dist: matplotlib
Requires-Dist: networkx
Requires-Dist: nltk
Requires-Dist: numpy
Requires-Dist: pandas
Requires-Dist: Pillow
Requires-Dist: scikit-learn
Requires-Dist: scikit-image
Requires-Dist: scipy
Requires-Dist: seaborn
Requires-Dist: statsmodels
Requires-Dist: tensorflow
Requires-Dist: GitPython
